Workbook

Sheet Inputs
A1: Example Co. DCF Workbook: Inputs
A2: Companion to the Discounted Cash Flow Valuation chapter. $ millions except per-share. Example Co. figures are invented for teaching.
A3: Legend: blue text = input you may change (yellow fill = key assumption); black = formula; green = link from another sheet.
A4: Input | B4: Value | C4: Source / note
A5: Base-year revenue | B5: 1000 | C5: From the Financial Statements chapter (Example Co.)
A6: Operating margin (EBIT / revenue) | B6: 0.15 | C6: 150 / 1,000; held constant in the forecast
A7: Tax rate | B7: 0.3 | C7: Marginal and effective rate assumed equal for teaching
A8: Sales-to-invested-capital (incremental) | B8: 1.1 | C8: Base year is 1,000 / 900 = 1.11; reinvestment = change in revenue / this ratio
A9: Cash | B9: 100 | C9: Base-year balance sheet
A10: Debt (book value as proxy for market value) | B10: 400 | C10: Base-year balance sheet
A11: Shares outstanding (millions) | B11: 100 | C11: Assumed for teaching; Example Co. has no reported share count
A12: Risk-free rate | B12: 0.04 | C12: ASSUMED for teaching, not current market data; check the current Treasury yield
A13: Beta (relevered bottom-up) | B13: 1.1 | C13: ASSUMED industry beta, relevered
A14: Equity risk premium | B14: 0.05 | C14: ASSUMED for teaching; check the current implied premium
A15: Pre-tax cost of debt | B15: 0.06 | C15: ASSUMED current long-term rate for the firm's rating
A16: Target debt weight, D/(D+E) | B16: 0.3 | C16: Target, not today's book ratio
... A19: Assumed market price per share ($) | B19: 18 | C19: ILLUSTRATIVE price used by the reverse DCF; Example Co. is not traded
A21: Cost of capital (formulas)
A22: Cost of equity = Rf + Beta x ERP | B22: =B12+B13*B14 -> 0.095
A23: After-tax cost of debt = Kd x (1 - tax) | B23: =B15*(1-B7) -> 0.042
A24: WACC | B24: =(1-B16)*B22+B16*B23 -> 0.0791 | C24: Weights are the target weights in B16

Sheet DCF
A1: Example Co.: Ten-Year FCFF Valuation
A2: End-of-year discounting in column B of the valuation block; mid-year shown in column C. $ millions.
A3: Year | B3: 0 | C3: 1 | D3: 2 | E3: 3 | F3: 4 | G3: 5 | H3: 6 | I3: 7 | J3: 8 | K3: 9 | L3: 10
A4: Revenue growth | C4: 0.08 | D4: 0.08 | E4: 0.08 | F4: 0.08 | G4: 0.08 | H4: 0.07 | I4: 0.06 | J4: 0.05 | K4: 0.04 | L4: 0.03
A5: Revenue | B5: =Inputs!B5 -> 1000 | C5: =B5*(1+C4) -> 1080 | D5: =C5*(1+D4) -> 1166.4 | E5: =D5*(1+E4) -> 1259.712 | F5: =E5*(1+F4) -> 1360.489 | G5: =F5*(1+G4) -> 1469.3281 | H5: =G5*(1+H4) -> 1572.181 | I5: =H5*(1+I4) -> 1666.5119 | J5: =I5*(1+J4) -> 1749.8375 | ... L5: =K5*(1+L4) -> 1874.4259
A6: EBIT | B6: =B5*Inputs!$B$6 -> 150 | C6: =C5*Inputs!$B$6 -> 162 | D6: =D5*Inputs!$B$6 -> 174.96 | E6: =E5*Inputs!$B$6 -> 188.9568 | F6: =F5*Inputs!$B$6 -> 204.07334 | G6: =G5*Inputs!$B$6 -> 220.39921 | H6: =H5*Inputs!$B$6 -> 235.82716 | I6: =I5*Inputs!$B$6 -> 249.97679 | ... L6: =L5*Inputs!$B$6 -> 281.16389
A7: NOPAT = EBIT x (1 - tax) | B7: =B6*(1-Inputs!$B$7) -> 105 | C7: =C6*(1-Inputs!$B$7) -> 113.4 | D7: =D6*(1-Inputs!$B$7) -> 122.472 | E7: =E6*(1-Inputs!$B$7) -> 132.26976 | F7: =F6*(1-Inputs!$B$7) -> 142.85134 | G7: =G6*(1-Inputs!$B$7) -> 154.27945 | H7: =H6*(1-Inputs!$B$7) -> 165.07901 | I7: =I6*(1-Inputs!$B$7) -> 174.98375 | ... L7: =L6*(1-Inputs!$B$7) -> 196.81472
A8: Reinvestment = change in revenue / sales-to-capital | C8: =(C5-B5)/Inputs!$B$8 -> 72.727273 | D8: =(D5-C5)/Inputs!$B$8 -> 78.545455 | E8: =(E5-D5)/Inputs!$B$8 -> 84.829091 | F8: =(F5-E5)/Inputs!$B$8 -> 91.615418 | G8: =(G5-F5)/Inputs!$B$8 -> 98.944652 | H8: =(H5-G5)/Inputs!$B$8 -> 93.502696 | I8: =(I5-H5)/Inputs!$B$8 -> 85.75533 | J8: =(J5-I5)/Inputs!$B$8 -> 75.750541 | ... L8: =(L5-K5)/Inputs!$B$8 -> 49.631755
A9: FCFF = NOPAT - reinvestment | C9: =C7-C8 -> 40.672727 | D9: =D7-D8 -> 43.926545 | E9: =E7-E8 -> 47.440669 | F9: =F7-F8 -> 51.235923 | G9: =G7-G8 -> 55.334796 | H9: =H7-H8 -> 71.576314 | I9: =I7-I8 -> 89.22842 | J9: =J7-J8 -> 107.9824 | ... L9: =L7-L8 -> 147.18297
A10: Discount factor at WACC | C10: =1/(1+Inputs!$B$24)^C3 -> 0.92669817 | D10: =1/(1+Inputs!$B$24)^D3 -> 0.85876951 | E10: =1/(1+Inputs!$B$24)^E3 -> 0.79582013 | F10: =1/(1+Inputs!$B$24)^F3 -> 0.73748507 | G10: =1/(1+Inputs!$B$24)^G3 -> 0.68342606 | H10: =1/(1+Inputs!$B$24)^H3 -> 0.63332969 | I10: =1/(1+Inputs!$B$24)^I3 -> 0.58690546 | J10: =1/(1+Inputs!$B$24)^J3 -> 0.54388422 | ... L10: =1/(1+Inputs!$B$24)^L3 -> 0.46707118
A11: PV of FCFF | C11: =C9*C10 -> 37.691342 | D11: =D9*D10 -> 37.722778 | E11: =E9*E10 -> 37.75424 | F11: =F9*F10 -> 37.785728 | G11: =G9*G10 -> 37.817242 | H11: =H9*H10 -> 45.331404 | I11: =I9*I10 -> 52.368647 | J11: =J9*J10 -> 58.729922 | ... L11: =L9*L10 -> 68.744923
A12: WACC used | B12: =Inputs!B24 -> 0.0791
A14: Terminal value (end of year 10)
A15: Stable growth, g | B15: =Inputs!B17 -> 0.03
A16: Terminal ROIC | B16: =Inputs!B18 -> 0.1
A17: Terminal reinvestment rate = g / ROIC | B17: =B15/B16 -> 0.3
A18: Year-11 NOPAT = year-10 NOPAT x (1 + g) | B18: =L7*(1+B15) -> 202.71916
A19: Year-11 FCFF = NOPAT x (1 - reinvestment rate) | B19: =B18*(1-B17) -> 141.90342
A20: Terminal value = FCFF11 / (WACC - g) | B20: =IF(B12>B15,B19/(B12-B15),NA()) -> 2890.0899
A21: PV of terminal value | B21: =B20*L10 -> 1349.8777
A23: Valuation | B23: End-of-year | C23: Mid-year
A24: PV of FCFF, years 1-5 | B24: =SUM(C11:G11) -> 188.77133
A25: PV of FCFF, years 6-10 | B25: =SUM(H11:L11) -> 289.41271
A26: PV of terminal value | B26: =B21 -> 1349.8777
A27: Enterprise value (operating assets) | B27: =SUM(B24:B26) -> 1828.0618 | C27: =B27*(1+B12)^0.5 -> 1898.9858
A28: + Cash | B28: =Inputs!B9 -> 100 | C28: =Inputs!B9 -> 100
A29: - Debt | B29: =-Inputs!B10 -> -400 | C29: =-Inputs!B10 -> -400
A30: Equity value | B30: =SUM(B27:B29) -> 1528.0618 | C30: =SUM(C27:C29) -> 1598.9858
A31: Shares outstanding (millions) | B31: =Inputs!B11 -> 100 | C31: =Inputs!B11 -> 100
A32: Value per share ($) | B32: =B30/B31 -> 15.280618 | C32: =C30/C31 -> 15.989858
A34: Cross-checks
A35: Terminal value as % of enterprise value | B35: =B26/B27 -> 0.7384202
A36: Enterprise value / base-year EBIT | B36: =B27/B6 -> 12.187078
A37: Enterprise value / base-year NOPAT | B37: =B27/B7 -> 17.410112
A38: Equity value / book equity (600) | B38: =B30/600 -> 2.5467696 | C38: Book equity of 600 from the Financial Statements chapter
A39: Year-10 reinvestment rate (compare with terminal) | B39: =L8/L7 -> 0.25217501
A40: Mid-year uplift to enterprise value | B40: =C27/B27-1 -> 0.038797382

Sheet Sensitivity
A1: Sensitivity Tables (plain formulas, no Excel data tables)
A2: Each cell recomputes value per share. "nmf" = not meaningful (WACC does not exceed growth).
A4: Table 1. Value per share ($): WACC (rows) by terminal growth (columns); reinvestment = g / terminal ROIC
A5: WACC \ g | B5: 0.01 | C5: 0.02 | D5: 0.03 | E5: 0.04
A6: =Inputs!$B$24+(-0.01) -> 0.0691 | B6: =IF($A6<=B$5,"nmf",(SUMPRODUCT(DCF!$C$9:$L$9/(1+$A6)^DCF!$C$3:$L$3)+DCF!$L$7*(1+B$5)*(1-B$5/Inputs!$B$18)/($A6-B$5)/(1+$A6)^DCF!$L$3+Inputs!$B$9-Inputs!$B$10)/Inputs!$B$11) -> 17.583985 | C6: =IF($A6<=C$5,"nmf",(SUMPRODUCT(DCF!$C$9:$L$9/(1+$A6)^DCF!$C$3:$L$3)+DCF!$L$7*(1+C$5)*(1-C$5/Inputs!$B$18)/($A6-C$5)/(1+$A6)^DCF!$L$3+Inputs!$B$9-Inputs!$B$10)/Inputs!$B$11) -> 18.833517 | D6: =IF($A6<=D$5,"nmf",(SUMPRODUCT(DCF!$C$9:$L$9/(1+$A6)^DCF!$C$3:$L$3)+DCF!$L$7*(1+D$5)*(1-D$5/Inputs!$B$18)/($A6-D$5)/(1+$A6)^DCF!$L$3+Inputs!$B$9-Inputs!$B$10)/Inputs!$B$11) -> 20.670585 | E6: =IF($A6<=E$5,"nmf",(SUMPRODUCT(DCF!$C$9:$L$9/(1+$A6)^DCF!$C$3:$L$3)+DCF!$L$7*(1+E$5)*(1-E$5/Inputs!$B$18)/($A6-E$5)/(1+$A6)^DCF!$L$3+Inputs!$B$9-Inputs!$B$10)/Inputs!$B$11) -> 23.700899
A7: =Inputs!$B$24+(-0.005) -> 0.0741 | B7: =IF($A7<=B$5,"nmf",(SUMPRODUCT(DCF!$C$9:$L$9/(1+$A7)^DCF!$C$3:$L$3)+DCF!$L$7*(1+B$5)*(1-B$5/Inputs!$B$18)/($A7-B$5)/(1+$A7)^DCF!$L$3+Inputs!$B$9-Inputs!$B$10)/Inputs!$B$11) -> 15.576599 | C7: =IF($A7<=C$5,"nmf",(SUMPRODUCT(DCF!$C$9:$L$9/(1+$A7)^DCF!$C$3:$L$3)+DCF!$L$7*(1+C$5)*(1-C$5/Inputs!$B$18)/($A7-C$5)/(1+$A7)^DCF!$L$3+Inputs!$B$9-Inputs!$B$10)/Inputs!$B$11) -> 16.445397 | D7: =IF($A7<=D$5,"nmf",(SUMPRODUCT(DCF!$C$9:$L$9/(1+$A7)^DCF!$C$3:$L$3)+DCF!$L$7*(1+D$5)*(1-D$5/Inputs!$B$18)/($A7-D$5)/(1+$A7)^DCF!$L$3+Inputs!$B$9-Inputs!$B$10)/Inputs!$B$11) -> 17.664537 | E7: =IF($A7<=E$5,"nmf",(SUMPRODUCT(DCF!$C$9:$L$9/(1+$A7)^DCF!$C$3:$L$3)+DCF!$L$7*(1+E$5)*(1-E$5/Inputs!$B$18)/($A7-E$5)/(1+$A7)^DCF!$L$3+Inputs!$B$9-Inputs!$B$10)/Inputs!$B$11) -> 19.542235
A8: =Inputs!$B$24+(0) -> 0.0791 | B8: =IF($A8<=B$5,"nmf",(SUMPRODUCT(DCF!$C$9:$L$9/(1+$A8)^DCF!$C$3:$L$3)+DCF!$L$7*(1+B$5)*(1-B$5/Inputs!$B$18)/($A8-B$5)/(1+$A8)^DCF!$L$3+Inputs!$B$9-Inputs!$B$10)/Inputs!$B$11) -> 13.87463 | C8: =IF($A8<=C$5,"nmf",(SUMPRODUCT(DCF!$C$9:$L$9/(1+$A8)^DCF!$C$3:$L$3)+DCF!$L$7*(1+C$5)*(1-C$5/Inputs!$B$18)/($A8-C$5)/(1+$A8)^DCF!$L$3+Inputs!$B$9-Inputs!$B$10)/Inputs!$B$11) -> 14.474228 | D8: =IF($A8<=D$5,"nmf",(SUMPRODUCT(DCF!$C$9:$L$9/(1+$A8)^DCF!$C$3:$L$3)+DCF!$L$7*(1+D$5)*(1-D$5/Inputs!$B$18)/($A8-D$5)/(1+$A8)^DCF!$L$3+Inputs!$B$9-Inputs!$B$10)/Inputs!$B$11) -> 15.280618 | E8: =IF($A8<=E$5,"nmf",(SUMPRODUCT(DCF!$C$9:$L$9/(1+$A8)^DCF!$C$3:$L$3)+DCF!$L$7*(1+E$5)*(1-E$5/Inputs!$B$18)/($A8-E$5)/(1+$A8)^DCF!$L$3+Inputs!$B$9-Inputs!$B$10)/Inputs!$B$11) -> 16.452461
A9: =Inputs!$B$24+(0.005) -> 0.0841 | B9: =IF($A9<=B$5,"nmf",(SUMPRODUCT(DCF!$C$9:$L$9/(1+$A9)^DCF!$C$3:$L$3)+DCF!$L$7*(1+B$5)*(1-B$5/Inputs!$B$18)/($A9-B$5)/(1+$A9)^DCF!$L$3+Inputs!$B$9-Inputs!$B$10)/Inputs!$B$11) -> 12.415609 | C9: =IF($A9<=C$5,"nmf",(SUMPRODUCT(DCF!$C$9:$L$9/(1+$A9)^DCF!$C$3:$L$3)+DCF!$L$7*(1+C$5)*(1-C$5/Inputs!$B$18)/($A9-C$5)/(1+$A9)^DCF!$L$3+Inputs!$B$9-Inputs!$B$10)/Inputs!$B$11) -> 12.821916 | D9: =IF($A9<=D$5,"nmf",(SUMPRODUCT(DCF!$C$9:$L$9/(1+$A9)^DCF!$C$3:$L$3)+DCF!$L$7*(1+D$5)*(1-D$5/Inputs!$B$18)/($A9-D$5)/(1+$A9)^DCF!$L$3+Inputs!$B$9-Inputs!$B$10)/Inputs!$B$11) -> 13.345979 | E9: =IF($A9<=E$5,"nmf",(SUMPRODUCT(DCF!$C$9:$L$9/(1+$A9)^DCF!$C$3:$L$3)+DCF!$L$7*(1+E$5)*(1-E$5/Inputs!$B$18)/($A9-E$5)/(1+$A9)^DCF!$L$3+Inputs!$B$9-Inputs!$B$10)/Inputs!$B$11) -> 14.067907
A10: =Inputs!$B$24+(0.01) -> 0.0891 | B10: =IF($A10<=B$5,"nmf",(SUMPRODUCT(DCF!$C$9:$L$9/(1+$A10)^DCF!$C$3:$L$3)+DCF!$L$7*(1+B$5)*(1-B$5/Inputs!$B$18)/($A10-B$5)/(1+$A10)^DCF!$L$3+Inputs!$B$9-Inputs!$B$10)/Inputs!$B$11) -> 11.152892 | C10: =IF($A10<=C$5,"nmf",(SUMPRODUCT(DCF!$C$9:$L$9/(1+$A10)^DCF!$C$3:$L$3)+DCF!$L$7*(1+C$5)*(1-C$5/Inputs!$B$18)/($A10-C$5)/(1+$A10)^DCF!$L$3+Inputs!$B$9-Inputs!$B$10)/Inputs!$B$11) -> 11.41878 | D10: =IF($A10<=D$5,"nmf",(SUMPRODUCT(DCF!$C$9:$L$9/(1+$A10)^DCF!$C$3:$L$3)+DCF!$L$7*(1+D$5)*(1-D$5/Inputs!$B$18)/($A10-D$5)/(1+$A10)^DCF!$L$3+Inputs!$B$9-Inputs!$B$10)/Inputs!$B$11) -> 11.74628 | E10: =IF($A10<=E$5,"nmf",(SUMPRODUCT(DCF!$C$9:$L$9/(1+$A10)^DCF!$C$3:$L$3)+DCF!$L$7*(1+E$5)*(1-E$5/Inputs!$B$18)/($A10-E$5)/(1+$A10)^DCF!$L$3+Inputs!$B$9-Inputs!$B$10)/Inputs!$B$11) -> 12.173036
A12: Terminal growth of 4% equals the assumed risk-free rate, the practical ceiling.
A14: Table 2. Terminal value ($ millions) by growth and terminal ROIC, holding year-11 NOPAT at the base-case figure
A15: g \ ROIC | B15: =Inputs!B24 -> 0.0791 | C15: 0.1 | D15: 0.15 | E15: 0.2
A16: 0.01 | B16: =DCF!$B$18*(1-$A16/B$15)/(DCF!$B$12-$A16) -> 2562.8213 | C16: =DCF!$B$18*(1-$A16/C$15)/(DCF!$B$12-$A16) -> 2640.3364 | D16: =DCF!$B$18*(1-$A16/D$15)/(DCF!$B$12-$A16) -> 2738.1267 | E16: =DCF!$B$18*(1-$A16/E$15)/(DCF!$B$12-$A16) -> 2787.0218
A17: 0.02 | B17: =DCF!$B$18*(1-$A17/B$15)/(DCF!$B$12-$A17) -> 2562.8213 | C17: =DCF!$B$18*(1-$A17/C$15)/(DCF!$B$12-$A17) -> 2744.0834 | D17: =DCF!$B$18*(1-$A17/D$15)/(DCF!$B$12-$A17) -> 2972.7571 | E17: =DCF!$B$18*(1-$A17/E$15)/(DCF!$B$12-$A17) -> 3087.0939
A18: 0.03 | B18: =DCF!$B$18*(1-$A18/B$15)/(DCF!$B$12-$A18) -> 2562.8213 | C18: =DCF!$B$18*(1-$A18/C$15)/(DCF!$B$12-$A18) -> 2890.0899 | D18: =DCF!$B$18*(1-$A18/D$15)/(DCF!$B$12-$A18) -> 3302.9599 | E18: =DCF!$B$18*(1-$A18/E$15)/(DCF!$B$12-$A18) -> 3509.3949
A19: 0.04 | B19: =DCF!$B$18*(1-$A19/B$15)/(DCF!$B$12-$A19) -> 2562.8213 | C19: =DCF!$B$18*(1-$A19/C$15)/(DCF!$B$12-$A19) -> 3110.78 | D19: =DCF!$B$18*(1-$A19/D$15)/(DCF!$B$12-$A19) -> 3802.0645 | E19: =DCF!$B$18*(1-$A19/E$15)/(DCF!$B$12-$A19) -> 4147.7067
A20: With ROIC = WACC (first column) growth adds no value; the higher the ROIC, the more growth adds.
A22: Table 3. Value per share ($): simple template (grow year-10 FCFF at g) vs reinvestment-consistent method
A23: Terminal growth | B23: Consistent reinvestment rate | C23: Simple template | D23: Consistent method
A24: 0.01 | B24: =A24/Inputs!$B$18 -> 0.1 | C24: =(SUMPRODUCT(DCF!$C$9:$L$9/(1+DCF!$B$12)^DCF!$C$3:$L$3)+DCF!$L$9*(1+A24)/(DCF!$B$12-A24)/(1+DCF!$B$12)^DCF!$L$3+Inputs!$B$9-Inputs!$B$10)/Inputs!$B$11 -> 11.829941 | D24: =(SUMPRODUCT(DCF!$C$9:$L$9/(1+DCF!$B$12)^DCF!$C$3:$L$3)+DCF!$L$7*(1+A24)*(1-A24/Inputs!$B$18)/(DCF!$B$12-A24)/(1+DCF!$B$12)^DCF!$L$3+Inputs!$B$9-Inputs!$B$10)/Inputs!$B$11 -> 13.87463
A25: 0.02 | B25: =A25/Inputs!$B$18 -> 0.2 | C25: =(SUMPRODUCT(DCF!$C$9:$L$9/(1+DCF!$B$12)^DCF!$C$3:$L$3)+DCF!$L$9*(1+A25)/(DCF!$B$12-A25)/(1+DCF!$B$12)^DCF!$L$3+Inputs!$B$9-Inputs!$B$10)/Inputs!$B$11 -> 13.646446 | D25: =(SUMPRODUCT(DCF!$C$9:$L$9/(1+DCF!$B$12)^DCF!$C$3:$L$3)+DCF!$L$7*(1+A25)*(1-A25/Inputs!$B$18)/(DCF!$B$12-A25)/(1+DCF!$B$12)^DCF!$L$3+Inputs!$B$9-Inputs!$B$10)/Inputs!$B$11 -> 14.474228
A26: 0.03 | B26: =A26/Inputs!$B$18 -> 0.3 | C26: =(SUMPRODUCT(DCF!$C$9:$L$9/(1+DCF!$B$12)^DCF!$C$3:$L$3)+DCF!$L$9*(1+A26)/(DCF!$B$12-A26)/(1+DCF!$B$12)^DCF!$L$3+Inputs!$B$9-Inputs!$B$10)/Inputs!$B$11 -> 16.202873 | D26: =(SUMPRODUCT(DCF!$C$9:$L$9/(1+DCF!$B$12)^DCF!$C$3:$L$3)+DCF!$L$7*(1+A26)*(1-A26/Inputs!$B$18)/(DCF!$B$12-A26)/(1+DCF!$B$12)^DCF!$L$3+Inputs!$B$9-Inputs!$B$10)/Inputs!$B$11 -> 15.280618
A27: 0.04 | B27: =A27/Inputs!$B$18 -> 0.4 | C27: =(SUMPRODUCT(DCF!$C$9:$L$9/(1+DCF!$B$12)^DCF!$C$3:$L$3)+DCF!$L$9*(1+A27)/(DCF!$B$12-A27)/(1+DCF!$B$12)^DCF!$L$3+Inputs!$B$9-Inputs!$B$10)/Inputs!$B$11 -> 20.066935 | D27: =(SUMPRODUCT(DCF!$C$9:$L$9/(1+DCF!$B$12)^DCF!$C$3:$L$3)+DCF!$L$7*(1+A27)*(1-A27/Inputs!$B$18)/(DCF!$B$12-A27)/(1+DCF!$B$12)^DCF!$L$3+Inputs!$B$9-Inputs!$B$10)/Inputs!$B$11 -> 16.452461
A28: 0.05 | B28: =A28/Inputs!$B$18 -> 0.5 | C28: =(SUMPRODUCT(DCF!$C$9:$L$9/(1+DCF!$B$12)^DCF!$C$3:$L$3)+DCF!$L$9*(1+A28)/(DCF!$B$12-A28)/(1+DCF!$B$12)^DCF!$L$3+Inputs!$B$9-Inputs!$B$10)/Inputs!$B$11 -> 26.58671 | D28: =(SUMPRODUCT(DCF!$C$9:$L$9/(1+DCF!$B$12)^DCF!$C$3:$L$3)+DCF!$L$7*(1+A28)*(1-A28/Inputs!$B$18)/(DCF!$B$12-A28)/(1+DCF!$B$12)^DCF!$L$3+Inputs!$B$9-Inputs!$B$10)/Inputs!$B$11 -> 18.366516
A29: The simple template holds reinvestment at its year-10 level whatever g is, so it undervalues at low g and overvalues at high g.

Sheet ReverseDCF
A1: Reverse DCF: What Growth Does the Price Imply?
A2: Years 1-5 revenue growth is the row input; growth then fades in a straight line to the terminal rate by year 10. All else follows the Inputs sheet.
A4: Assumed market price ($) | B4: =Inputs!B19 -> 18
A5: Implied years 1-5 growth (interpolated) | B5: =IFERROR(INDEX($A$9:$A$19,MATCH(B4,$AF$9:$AF$19,1))+(B4-INDEX($AF$9:$AF$19,MATCH(B4,$AF$9:$AF$19,1)))/(INDEX($AF$9:$AF$19,MATCH(B4,$AF$9:$AF$19,1)+1)-INDEX($AF$9:$AF$19,MATCH(B4,$AF$9:$AF$19,1)))*0.02,"outside 0-20% grid") -> 0.12289161
A6: Exact answer: Data > What-If Analysis > Goal Seek. Set DCF!B32 (value per share) to the price by changing one growth cell, or set it by changing the risk-free rate (Inputs!B12) to see the implied discount rate.
A7: Year | B7: 1 | C7: 2 | D7: 3 | E7: 4 | F7: 5 | G7: 6 | H7: 7 | I7: 8 | J7: 9 | K7: 10
A8: Starting growth | B8: Growth y1 | C8: Growth y2 | D8: Growth y3 | E8: Growth y4 | F8: Growth y5 | G8: Growth y6 | H8: Growth y7 | I8: Growth y8 | J8: Growth y9 | K8: Growth y10 | L8: Revenue y1 | M8: Revenue y2 | N8: Revenue y3 | O8: Revenue y4 | P8: Revenue y5 | Q8: Revenue y6 | R8: Revenue y7 | S8: Revenue y8 | T8: Revenue y9 | U8: Revenue y10 | V8: FCFF y1 | W8: FCFF y2 | X8: FCFF y3 | Y8: FCFF y4 | Z8: FCFF y5 | AA8: FCFF y6 | AB8: FCFF y7 | AC8: FCFF y8 | AD8: FCFF y9 | AE8: FCFF y10 | AF8: Value per share ($)
A9: 0 | B9: =$A9 -> 0 | C9: =$A9 -> 0 | D9: =$A9 -> 0 | E9: =$A9 -> 0 | F9: =$A9 -> 0 | G9: =$A9+(Inputs!$B$17-$A9)*(G$7-5)/5 -> 0.006 | H9: =$A9+(Inputs!$B$17-$A9)*(H$7-5)/5 -> 0.012 | I9: =$A9+(Inputs!$B$17-$A9)*(I$7-5)/5 -> 0.018 | J9: =$A9+(Inputs!$B$17-$A9)*(J$7-5)/5 -> 0.024 | K9: =$A9+(Inputs!$B$17-$A9)*(K$7-5)/5 -> 0.03 | L9: =Inputs!$B$5*(1+B9) -> 1000 | M9: =L9*(1+C9) -> 1000 | N9: =M9*(1+D9) -> 1000 | O9: =N9*(1+E9) -> 1000 | P9: =O9*(1+F9) -> 1000 | Q9: =P9*(1+G9) -> 1006 | R9: =Q9*(1+H9) -> 1018.072 | S9: =R9*(1+I9) -> 1036.3973 | T9: =S9*(1+J9) -> 1061.2708 | U9: =T9*(1+K9) -> 1093.109 | V9: =L9*Inputs!$B$6*(1-Inputs!$B$7)-(L9-Inputs!$B$5)/Inputs!$B$8 -> 105 | W9: =M9*Inputs!$B$6*(1-Inputs!$B$7)-(M9-L9)/Inputs!$B$8 -> 105 | X9: =N9*Inputs!$B$6*(1-Inputs!$B$7)-(N9-M9)/Inputs!$B$8 -> 105 | Y9: =O9*Inputs!$B$6*(1-Inputs!$B$7)-(O9-N9)/Inputs!$B$8 -> 105 | Z9: =P9*Inputs!$B$6*(1-Inputs!$B$7)-(P9-O9)/Inputs!$B$8 -> 105 | AA9: =Q9*Inputs!$B$6*(1-Inputs!$B$7)-(Q9-P9)/Inputs!$B$8 -> 100.17545 | AB9: =R9*Inputs!$B$6*(1-Inputs!$B$7)-(R9-Q9)/Inputs!$B$8 -> 95.923015 | AC9: =S9*Inputs!$B$6*(1-Inputs!$B$7)-(S9-R9)/Inputs!$B$8 -> 92.162356 | AD9: =T9*Inputs!$B$6*(1-Inputs!$B$7)-(T9-S9)/Inputs!$B$8 -> 88.821133 | AE9: =U9*Inputs!$B$6*(1-Inputs!$B$7)-(U9-T9)/Inputs!$B$8 -> 85.83269 | AF9: =(SUMPRODUCT(V9:AE9/(1+Inputs!$B$24)^$B$7:$K$7)+U9*Inputs!$B$6*(1-Inputs!$B$7)*(1+Inputs!$B$17)*(1-Inputs!$B$17/Inputs!$B$18)/(Inputs!$B$24-Inputs!$B$17)/(1+Inputs!$B$24)^$K$7+Inputs!$B$9-Inputs!$B$10)/Inputs!$B$11 -> 11.621638
A10: 0.02 | B10: =$A10 -> 0.02 | C10: =$A10 -> 0.02 | D10: =$A10 -> 0.02 | E10: =$A10 -> 0.02 | F10: =$A10 -> 0.02 | G10: =$A10+(Inputs!$B$17-$A10)*(G$7-5)/5 -> 0.022 | H10: =$A10+(Inputs!$B$17-$A10)*(H$7-5)/5 -> 0.024 | I10: =$A10+(Inputs!$B$17-$A10)*(I$7-5)/5 -> 0.026 | J10: =$A10+(Inputs!$B$17-$A10)*(J$7-5)/5 -> 0.028 | K10: =$A10+(Inputs!$B$17-$A10)*(K$7-5)/5 -> 0.03 | L10: =Inputs!$B$5*(1+B10) -> 1020 | M10: =L10*(1+C10) -> 1040.4 | N10: =M10*(1+D10) -> 1061.208 | O10: =N10*(1+E10) -> 1082.4322 | P10: =O10*(1+F10) -> 1104.0808 | Q10: =P10*(1+G10) -> 1128.3706 | R10: =Q10*(1+H10) -> 1155.4515 | S10: =R10*(1+I10) -> 1185.4932 | T10: =S10*(1+J10) -> 1218.687 | U10: =T10*(1+K10) -> 1255.2476 | V10: =L10*Inputs!$B$6*(1-Inputs!$B$7)-(L10-Inputs!$B$5)/Inputs!$B$8 -> 88.918182 | W10: =M10*Inputs!$B$6*(1-Inputs!$B$7)-(M10-L10)/Inputs!$B$8 -> 90.696545 | X10: =N10*Inputs!$B$6*(1-Inputs!$B$7)-(N10-M10)/Inputs!$B$8 -> 92.510476 | Y10: =O10*Inputs!$B$6*(1-Inputs!$B$7)-(O10-N10)/Inputs!$B$8 -> 94.360686 | Z10: =P10*Inputs!$B$6*(1-Inputs!$B$7)-(P10-O10)/Inputs!$B$8 -> 96.2479 | AA10: =Q10*Inputs!$B$6*(1-Inputs!$B$7)-(Q10-P10)/Inputs!$B$8 -> 96.397295 | AB10: =R10*Inputs!$B$6*(1-Inputs!$B$7)-(R10-Q10)/Inputs!$B$8 -> 96.70341 | AC10: =S10*Inputs!$B$6*(1-Inputs!$B$7)-(S10-R10)/Inputs!$B$8 -> 97.166116 | AD10: =T10*Inputs!$B$6*(1-Inputs!$B$7)-(T10-S10)/Inputs!$B$8 -> 97.785947 | AE10: =U10*Inputs!$B$6*(1-Inputs!$B$7)-(U10-T10)/Inputs!$B$8 -> 98.564083 | AF10: =(SUMPRODUCT(V10:AE10/(1+Inputs!$B$24)^$B$7:$K$7)+U10*Inputs!$B$6*(1-Inputs!$B$7)*(1+Inputs!$B$17)*(1-Inputs!$B$17/Inputs!$B$18)/(Inputs!$B$24-Inputs!$B$17)/(1+Inputs!$B$24)^$K$7+Inputs!$B$9-Inputs!$B$10)/Inputs!$B$11 -> 12.392269
A11: 0.04 | B11: =$A11 -> 0.04 | C11: =$A11 -> 0.04 | D11: =$A11 -> 0.04 | E11: =$A11 -> 0.04 | F11: =$A11 -> 0.04 | G11: =$A11+(Inputs!$B$17-$A11)*(G$7-5)/5 -> 0.038 | H11: =$A11+(Inputs!$B$17-$A11)*(H$7-5)/5 -> 0.036 | I11: =$A11+(Inputs!$B$17-$A11)*(I$7-5)/5 -> 0.034 | J11: =$A11+(Inputs!$B$17-$A11)*(J$7-5)/5 -> 0.032 | K11: =$A11+(Inputs!$B$17-$A11)*(K$7-5)/5 -> 0.03 | L11: =Inputs!$B$5*(1+B11) -> 1040 | M11: =L11*(1+C11) -> 1081.6 | N11: =M11*(1+D11) -> 1124.864 | O11: =N11*(1+E11) -> 1169.8586 | P11: =O11*(1+F11) -> 1216.6529 | Q11: =P11*(1+G11) -> 1262.8857 | R11: =Q11*(1+H11) -> 1308.3496 | S11: =R11*(1+I11) -> 1352.8335 | T11: =S11*(1+J11) -> 1396.1242 | U11: =T11*(1+K11) -> 1438.0079 | V11: =L11*Inputs!$B$6*(1-Inputs!$B$7)-(L11-Inputs!$B$5)/Inputs!$B$8 -> 72.836364 | W11: =M11*Inputs!$B$6*(1-Inputs!$B$7)-(M11-L11)/Inputs!$B$8 -> 75.749818 | X11: =N11*Inputs!$B$6*(1-Inputs!$B$7)-(N11-M11)/Inputs!$B$8 -> 78.779811 | Y11: =O11*Inputs!$B$6*(1-Inputs!$B$7)-(O11-N11)/Inputs!$B$8 -> 81.931003 | Z11: =P11*Inputs!$B$6*(1-Inputs!$B$7)-(P11-O11)/Inputs!$B$8 -> 85.208243 | AA11: =Q11*Inputs!$B$6*(1-Inputs!$B$7)-(Q11-P11)/Inputs!$B$8 -> 90.573172 | AB11: =R11*Inputs!$B$6*(1-Inputs!$B$7)-(R11-Q11)/Inputs!$B$8 -> 96.045903 | AC11: =S11*Inputs!$B$6*(1-Inputs!$B$7)-(S11-R11)/Inputs!$B$8 -> 101.60762 | AD11: =T11*Inputs!$B$6*(1-Inputs!$B$7)-(T11-S11)/Inputs!$B$8 -> 107.23788 | AE11: =U11*Inputs!$B$6*(1-Inputs!$B$7)-(U11-T11)/Inputs!$B$8 -> 112.91471 | AF11: =(SUMPRODUCT(V11:AE11/(1+Inputs!$B$24)^$B$7:$K$7)+U11*Inputs!$B$6*(1-Inputs!$B$7)*(1+Inputs!$B$17)*(1-Inputs!$B$17/Inputs!$B$18)/(Inputs!$B$24-Inputs!$B$17)/(1+Inputs!$B$24)^$K$7+Inputs!$B$9-Inputs!$B$10)/Inputs!$B$11 -> 13.252731
A12: 0.06 | B12: =$A12 -> 0.06 | C12: =$A12 -> 0.06 | D12: =$A12 -> 0.06 | E12: =$A12 -> 0.06 | F12: =$A12 -> 0.06 | G12: =$A12+(Inputs!$B$17-$A12)*(G$7-5)/5 -> 0.054 | H12: =$A12+(Inputs!$B$17-$A12)*(H$7-5)/5 -> 0.048 | I12: =$A12+(Inputs!$B$17-$A12)*(I$7-5)/5 -> 0.042 | J12: =$A12+(Inputs!$B$17-$A12)*(J$7-5)/5 -> 0.036 | K12: =$A12+(Inputs!$B$17-$A12)*(K$7-5)/5 -> 0.03 | L12: =Inputs!$B$5*(1+B12) -> 1060 | M12: =L12*(1+C12) -> 1123.6 | N12: =M12*(1+D12) -> 1191.016 | O12: =N12*(1+E12) -> 1262.477 | P12: =O12*(1+F12) -> 1338.2256 | Q12: =P12*(1+G12) -> 1410.4898 | R12: =Q12*(1+H12) -> 1478.1933 | S12: =R12*(1+I12) -> 1540.2774 | T12: =S12*(1+J12) -> 1595.7274 | U12: =T12*(1+K12) -> 1643.5992 | V12: =L12*Inputs!$B$6*(1-Inputs!$B$7)-(L12-Inputs!$B$5)/Inputs!$B$8 -> 56.754545 | W12: =M12*Inputs!$B$6*(1-Inputs!$B$7)-(M12-L12)/Inputs!$B$8 -> 60.159818 | X12: =N12*Inputs!$B$6*(1-Inputs!$B$7)-(N12-M12)/Inputs!$B$8 -> 63.769407 | Y12: =O12*Inputs!$B$6*(1-Inputs!$B$7)-(O12-N12)/Inputs!$B$8 -> 67.595572 | Z12: =P12*Inputs!$B$6*(1-Inputs!$B$7)-(P12-O12)/Inputs!$B$8 -> 71.651306 | AA12: =Q12*Inputs!$B$6*(1-Inputs!$B$7)-(Q12-P12)/Inputs!$B$8 -> 82.406714 | AB12: =R12*Inputs!$B$6*(1-Inputs!$B$7)-(R12-Q12)/Inputs!$B$8 -> 93.661649 | AC12: =S12*Inputs!$B$6*(1-Inputs!$B$7)-(S12-R12)/Inputs!$B$8 -> 105.28902 | AD12: =T12*Inputs!$B$6*(1-Inputs!$B$7)-(T12-S12)/Inputs!$B$8 -> 117.1423 | AE12: =U12*Inputs!$B$6*(1-Inputs!$B$7)-(U12-T12)/Inputs!$B$8 -> 129.05808 | AF12: =(SUMPRODUCT(V12:AE12/(1+Inputs!$B$24)^$B$7:$K$7)+U12*Inputs!$B$6*(1-Inputs!$B$7)*(1+Inputs!$B$17)*(1-Inputs!$B$17/Inputs!$B$18)/(Inputs!$B$24-Inputs!$B$17)/(1+Inputs!$B$24)^$K$7+Inputs!$B$9-Inputs!$B$10)/Inputs!$B$11 -> 14.212196
A13: 0.08 | B13: =$A13 -> 0.08 | C13: =$A13 -> 0.08 | D13: =$A13 -> 0.08 | E13: =$A13 -> 0.08 | F13: =$A13 -> 0.08 | G13: =$A13+(Inputs!$B$17-$A13)*(G$7-5)/5 -> 0.07 | H13: =$A13+(Inputs!$B$17-$A13)*(H$7-5)/5 -> 0.06 | I13: =$A13+(Inputs!$B$17-$A13)*(I$7-5)/5 -> 0.05 | J13: =$A13+(Inputs!$B$17-$A13)*(J$7-5)/5 -> 0.04 | K13: =$A13+(Inputs!$B$17-$A13)*(K$7-5)/5 -> 0.03 | L13: =Inputs!$B$5*(1+B13) -> 1080 | M13: =L13*(1+C13) -> 1166.4 | N13: =M13*(1+D13) -> 1259.712 | O13: =N13*(1+E13) -> 1360.489 | P13: =O13*(1+F13) -> 1469.3281 | Q13: =P13*(1+G13) -> 1572.181 | R13: =Q13*(1+H13) -> 1666.5119 | S13: =R13*(1+I13) -> 1749.8375 | T13: =S13*(1+J13) -> 1819.831 | U13: =T13*(1+K13) -> 1874.4259 | V13: =L13*Inputs!$B$6*(1-Inputs!$B$7)-(L13-Inputs!$B$5)/Inputs!$B$8 -> 40.672727 | W13: =M13*Inputs!$B$6*(1-Inputs!$B$7)-(M13-L13)/Inputs!$B$8 -> 43.926545 | X13: =N13*Inputs!$B$6*(1-Inputs!$B$7)-(N13-M13)/Inputs!$B$8 -> 47.440669 | Y13: =O13*Inputs!$B$6*(1-Inputs!$B$7)-(O13-N13)/Inputs!$B$8 -> 51.235923 | Z13: =P13*Inputs!$B$6*(1-Inputs!$B$7)-(P13-O13)/Inputs!$B$8 -> 55.334796 | AA13: =Q13*Inputs!$B$6*(1-Inputs!$B$7)-(Q13-P13)/Inputs!$B$8 -> 71.576314 | AB13: =R13*Inputs!$B$6*(1-Inputs!$B$7)-(R13-Q13)/Inputs!$B$8 -> 89.22842 | AC13: =S13*Inputs!$B$6*(1-Inputs!$B$7)-(S13-R13)/Inputs!$B$8 -> 107.9824 | AD13: =T13*Inputs!$B$6*(1-Inputs!$B$7)-(T13-S13)/Inputs!$B$8 -> 127.4518 | AE13: =U13*Inputs!$B$6*(1-Inputs!$B$7)-(U13-T13)/Inputs!$B$8 -> 147.18297 | AF13: =(SUMPRODUCT(V13:AE13/(1+Inputs!$B$24)^$B$7:$K$7)+U13*Inputs!$B$6*(1-Inputs!$B$7)*(1+Inputs!$B$17)*(1-Inputs!$B$17/Inputs!$B$18)/(Inputs!$B$24-Inputs!$B$17)/(1+Inputs!$B$24)^$K$7+Inputs!$B$9-Inputs!$B$10)/Inputs!$B$11 -> 15.280618
A14: 0.1 | B14: =$A14 -> 0.1 | C14: =$A14 -> 0.1 | D14: =$A14 -> 0.1 | E14: =$A14 -> 0.1 | F14: =$A14 -> 0.1 | G14: =$A14+(Inputs!$B$17-$A14)*(G$7-5)/5 -> 0.086 | H14: =$A14+(Inputs!$B$17-$A14)*(H$7-5)/5 -> 0.072 | I14: =$A14+(Inputs!$B$17-$A14)*(I$7-5)/5 -> 0.058 | J14: =$A14+(Inputs!$B$17-$A14)*(J$7-5)/5 -> 0.044 | K14: =$A14+(Inputs!$B$17-$A14)*(K$7-5)/5 -> 0.03 | L14: =Inputs!$B$5*(1+B14) -> 1100 | M14: =L14*(1+C14) -> 1210 | N14: =M14*(1+D14) -> 1331 | O14: =N14*(1+E14) -> 1464.1 | P14: =O14*(1+F14) -> 1610.51 | Q14: =P14*(1+G14) -> 1749.0139 | R14: =Q14*(1+H14) -> 1874.9429 | S14: =R14*(1+I14) -> 1983.6895 | T14: =S14*(1+J14) -> 2070.9719 | U14: =T14*(1+K14) -> 2133.101 | V14: =L14*Inputs!$B$6*(1-Inputs!$B$7)-(L14-Inputs!$B$5)/Inputs!$B$8 -> 24.590909 | W14: =M14*Inputs!$B$6*(1-Inputs!$B$7)-(M14-L14)/Inputs!$B$8 -> 27.05 | X14: =N14*Inputs!$B$6*(1-Inputs!$B$7)-(N14-M14)/Inputs!$B$8 -> 29.755 | Y14: =O14*Inputs!$B$6*(1-Inputs!$B$7)-(O14-N14)/Inputs!$B$8 -> 32.7305 | Z14: =P14*Inputs!$B$6*(1-Inputs!$B$7)-(P14-O14)/Inputs!$B$8 -> 36.00355 | AA14: =Q14*Inputs!$B$6*(1-Inputs!$B$7)-(Q14-P14)/Inputs!$B$8 -> 57.733855 | AB14: =R14*Inputs!$B$6*(1-Inputs!$B$7)-(R14-Q14)/Inputs!$B$8 -> 82.388093 | AC14: =S14*Inputs!$B$6*(1-Inputs!$B$7)-(S14-R14)/Inputs!$B$8 -> 109.42678 | AD14: =T14*Inputs!$B$6*(1-Inputs!$B$7)-(T14-S14)/Inputs!$B$8 -> 138.10447 | AE14: =U14*Inputs!$B$6*(1-Inputs!$B$7)-(U14-T14)/Inputs!$B$8 -> 167.49456 | AF14: =(SUMPRODUCT(V14:AE14/(1+Inputs!$B$24)^$B$7:$K$7)+U14*Inputs!$B$6*(1-Inputs!$B$7)*(1+Inputs!$B$17)*(1-Inputs!$B$17/Inputs!$B$18)/(Inputs!$B$24-Inputs!$B$17)/(1+Inputs!$B$24)^$K$7+Inputs!$B$9-Inputs!$B$10)/Inputs!$B$11 -> 16.468786
A15: 0.12 | B15: =$A15 -> 0.12 | C15: =$A15 -> 0.12 | D15: =$A15 -> 0.12 | E15: =$A15 -> 0.12 | F15: =$A15 -> 0.12 | G15: =$A15+(Inputs!$B$17-$A15)*(G$7-5)/5 -> 0.102 | H15: =$A15+(Inputs!$B$17-$A15)*(H$7-5)/5 -> 0.084 | I15: =$A15+(Inputs!$B$17-$A15)*(I$7-5)/5 -> 0.066 | J15: =$A15+(Inputs!$B$17-$A15)*(J$7-5)/5 -> 0.048 | K15: =$A15+(Inputs!$B$17-$A15)*(K$7-5)/5 -> 0.03 | L15: =Inputs!$B$5*(1+B15) -> 1120 | M15: =L15*(1+C15) -> 1254.4 | N15: =M15*(1+D15) -> 1404.928 | O15: =N15*(1+E15) -> 1573.5194 | P15: =O15*(1+F15) -> 1762.3417 | Q15: =P15*(1+G15) -> 1942.1005 | R15: =Q15*(1+H15) -> 2105.237 | S15: =R15*(1+I15) -> 2244.1826 | T15: =S15*(1+J15) -> 2351.9034 | U15: =T15*(1+K15) -> 2422.4605 | V15: =L15*Inputs!$B$6*(1-Inputs!$B$7)-(L15-Inputs!$B$5)/Inputs!$B$8 -> 8.5090909 | W15: =M15*Inputs!$B$6*(1-Inputs!$B$7)-(M15-L15)/Inputs!$B$8 -> 9.5301818 | X15: =N15*Inputs!$B$6*(1-Inputs!$B$7)-(N15-M15)/Inputs!$B$8 -> 10.673804 | Y15: =O15*Inputs!$B$6*(1-Inputs!$B$7)-(O15-N15)/Inputs!$B$8 -> 11.95466 | Z15: =P15*Inputs!$B$6*(1-Inputs!$B$7)-(P15-O15)/Inputs!$B$8 -> 13.389219 | AA15: =Q15*Inputs!$B$6*(1-Inputs!$B$7)-(Q15-P15)/Inputs!$B$8 -> 40.503418 | AB15: =R15*Inputs!$B$6*(1-Inputs!$B$7)-(R15-Q15)/Inputs!$B$8 -> 72.744024 | AC15: =S15*Inputs!$B$6*(1-Inputs!$B$7)-(S15-R15)/Inputs!$B$8 -> 109.32496 | AD15: =T15*Inputs!$B$6*(1-Inputs!$B$7)-(T15-S15)/Inputs!$B$8 -> 149.02189 | AE15: =U15*Inputs!$B$6*(1-Inputs!$B$7)-(U15-T15)/Inputs!$B$8 -> 190.21553 | AF15: =(SUMPRODUCT(V15:AE15/(1+Inputs!$B$24)^$B$7:$K$7)+U15*Inputs!$B$6*(1-Inputs!$B$7)*(1+Inputs!$B$17)*(1-Inputs!$B$17/Inputs!$B$18)/(Inputs!$B$24-Inputs!$B$17)/(1+Inputs!$B$24)^$K$7+Inputs!$B$9-Inputs!$B$10)/Inputs!$B$11 -> 17.788383
A16: 0.14 | B16: =$A16 -> 0.14 | C16: =$A16 -> 0.14 | D16: =$A16 -> 0.14 | E16: =$A16 -> 0.14 | F16: =$A16 -> 0.14 | G16: =$A16+(Inputs!$B$17-$A16)*(G$7-5)/5 -> 0.118 | H16: =$A16+(Inputs!$B$17-$A16)*(H$7-5)/5 -> 0.096 | I16: =$A16+(Inputs!$B$17-$A16)*(I$7-5)/5 -> 0.074 | J16: =$A16+(Inputs!$B$17-$A16)*(J$7-5)/5 -> 0.052 | K16: =$A16+(Inputs!$B$17-$A16)*(K$7-5)/5 -> 0.03 | L16: =Inputs!$B$5*(1+B16) -> 1140 | M16: =L16*(1+C16) -> 1299.6 | N16: =M16*(1+D16) -> 1481.544 | O16: =N16*(1+E16) -> 1688.9602 | P16: =O16*(1+F16) -> 1925.4146 | Q16: =P16*(1+G16) -> 2152.6135 | R16: =Q16*(1+H16) -> 2359.2644 | S16: =R16*(1+I16) -> 2533.85 | T16: =S16*(1+J16) -> 2665.6102 | U16: =T16*(1+K16) -> 2745.5785 | V16: =L16*Inputs!$B$6*(1-Inputs!$B$7)-(L16-Inputs!$B$5)/Inputs!$B$8 -> -7.5727273 | W16: =M16*Inputs!$B$6*(1-Inputs!$B$7)-(M16-L16)/Inputs!$B$8 -> -8.6329091 | X16: =N16*Inputs!$B$6*(1-Inputs!$B$7)-(N16-M16)/Inputs!$B$8 -> -9.8415164 | Y16: =O16*Inputs!$B$6*(1-Inputs!$B$7)-(O16-N16)/Inputs!$B$8 -> -11.219329 | Z16: =P16*Inputs!$B$6*(1-Inputs!$B$7)-(P16-O16)/Inputs!$B$8 -> -12.790035 | AA16: =Q16*Inputs!$B$6*(1-Inputs!$B$7)-(Q16-P16)/Inputs!$B$8 -> 19.479944 | AB16: =R16*Inputs!$B$6*(1-Inputs!$B$7)-(R16-Q16)/Inputs!$B$8 -> 59.858311 | AC16: =S16*Inputs!$B$6*(1-Inputs!$B$7)-(S16-R16)/Inputs!$B$8 -> 107.3401 | AD16: =T16*Inputs!$B$6*(1-Inputs!$B$7)-(T16-S16)/Inputs!$B$8 -> 160.10707 | AE16: =U16*Inputs!$B$6*(1-Inputs!$B$7)-(U16-T16)/Inputs!$B$8 -> 215.58728 | AF16: =(SUMPRODUCT(V16:AE16/(1+Inputs!$B$24)^$B$7:$K$7)+U16*Inputs!$B$6*(1-Inputs!$B$7)*(1+Inputs!$B$17)*(1-Inputs!$B$17/Inputs!$B$18)/(Inputs!$B$24-Inputs!$B$17)/(1+Inputs!$B$24)^$K$7+Inputs!$B$9-Inputs!$B$10)/Inputs!$B$11 -> 19.252045
A17: 0.16 | B17: =$A17 -> 0.16 | C17: =$A17 -> 0.16 | D17: =$A17 -> 0.16 | E17: =$A17 -> 0.16 | F17: =$A17 -> 0.16 | G17: =$A17+(Inputs!$B$17-$A17)*(G$7-5)/5 -> 0.134 | H17: =$A17+(Inputs!$B$17-$A17)*(H$7-5)/5 -> 0.108 | I17: =$A17+(Inputs!$B$17-$A17)*(I$7-5)/5 -> 0.082 | J17: =$A17+(Inputs!$B$17-$A17)*(J$7-5)/5 -> 0.056 | K17: =$A17+(Inputs!$B$17-$A17)*(K$7-5)/5 -> 0.03 | L17: =Inputs!$B$5*(1+B17) -> 1160 | M17: =L17*(1+C17) -> 1345.6 | N17: =M17*(1+D17) -> 1560.896 | O17: =N17*(1+E17) -> 1810.6394 | P17: =O17*(1+F17) -> 2100.3417 | Q17: =P17*(1+G17) -> 2381.7874 | R17: =Q17*(1+H17) -> 2639.0205 | S17: =R17*(1+I17) -> 2855.4202 | T17: =S17*(1+J17) -> 3015.3237 | U17: =T17*(1+K17) -> 3105.7834 | V17: =L17*Inputs!$B$6*(1-Inputs!$B$7)-(L17-Inputs!$B$5)/Inputs!$B$8 -> -23.654545 | W17: =M17*Inputs!$B$6*(1-Inputs!$B$7)-(M17-L17)/Inputs!$B$8 -> -27.439273 | X17: =N17*Inputs!$B$6*(1-Inputs!$B$7)-(N17-M17)/Inputs!$B$8 -> -31.829556 | Y17: =O17*Inputs!$B$6*(1-Inputs!$B$7)-(O17-N17)/Inputs!$B$8 -> -36.922285 | Z17: =P17*Inputs!$B$6*(1-Inputs!$B$7)-(P17-O17)/Inputs!$B$8 -> -42.829851 | AA17: =Q17*Inputs!$B$6*(1-Inputs!$B$7)-(Q17-P17)/Inputs!$B$8 -> -5.7721208 | AB17: =R17*Inputs!$B$6*(1-Inputs!$B$7)-(R17-Q17)/Inputs!$B$8 -> 43.248929 | AC17: =S17*Inputs!$B$6*(1-Inputs!$B$7)-(S17-R17)/Inputs!$B$8 -> 103.09214 | AD17: =T17*Inputs!$B$6*(1-Inputs!$B$7)-(T17-S17)/Inputs!$B$8 -> 171.24214 | AE17: =U17*Inputs!$B$6*(1-Inputs!$B$7)-(U17-T17)/Inputs!$B$8 -> 243.87116 | AF17: =(SUMPRODUCT(V17:AE17/(1+Inputs!$B$24)^$B$7:$K$7)+U17*Inputs!$B$6*(1-Inputs!$B$7)*(1+Inputs!$B$17)*(1-Inputs!$B$17/Inputs!$B$18)/(Inputs!$B$24-Inputs!$B$17)/(1+Inputs!$B$24)^$K$7+Inputs!$B$9-Inputs!$B$10)/Inputs!$B$11 -> 20.87342
A18: 0.18 | B18: =$A18 -> 0.18 | C18: =$A18 -> 0.18 | D18: =$A18 -> 0.18 | E18: =$A18 -> 0.18 | F18: =$A18 -> 0.18 | G18: =$A18+(Inputs!$B$17-$A18)*(G$7-5)/5 -> 0.15 | H18: =$A18+(Inputs!$B$17-$A18)*(H$7-5)/5 -> 0.12 | I18: =$A18+(Inputs!$B$17-$A18)*(I$7-5)/5 -> 0.09 | J18: =$A18+(Inputs!$B$17-$A18)*(J$7-5)/5 -> 0.06 | K18: =$A18+(Inputs!$B$17-$A18)*(K$7-5)/5 -> 0.03 | L18: =Inputs!$B$5*(1+B18) -> 1180 | M18: =L18*(1+C18) -> 1392.4 | N18: =M18*(1+D18) -> 1643.032 | O18: =N18*(1+E18) -> 1938.7778 | P18: =O18*(1+F18) -> 2287.7578 | Q18: =P18*(1+G18) -> 2630.9214 | R18: =Q18*(1+H18) -> 2946.632 | S18: =R18*(1+I18) -> 3211.8289 | T18: =S18*(1+J18) -> 3404.5386 | U18: =T18*(1+K18) -> 3506.6748 | V18: =L18*Inputs!$B$6*(1-Inputs!$B$7)-(L18-Inputs!$B$5)/Inputs!$B$8 -> -39.736364 | W18: =M18*Inputs!$B$6*(1-Inputs!$B$7)-(M18-L18)/Inputs!$B$8 -> -46.888909 | X18: =N18*Inputs!$B$6*(1-Inputs!$B$7)-(N18-M18)/Inputs!$B$8 -> -55.328913 | Y18: =O18*Inputs!$B$6*(1-Inputs!$B$7)-(O18-N18)/Inputs!$B$8 -> -65.288117 | Z18: =P18*Inputs!$B$6*(1-Inputs!$B$7)-(P18-O18)/Inputs!$B$8 -> -77.039978 | AA18: =Q18*Inputs!$B$6*(1-Inputs!$B$7)-(Q18-P18)/Inputs!$B$8 -> -35.720218 | AB18: =R18*Inputs!$B$6*(1-Inputs!$B$7)-(R18-Q18)/Inputs!$B$8 -> 22.38675 | AC18: =S18*Inputs!$B$6*(1-Inputs!$B$7)-(S18-R18)/Inputs!$B$8 -> 96.153959 | AD18: =T18*Inputs!$B$6*(1-Inputs!$B$7)-(T18-S18)/Inputs!$B$8 -> 182.28589 | AE18: =U18*Inputs!$B$6*(1-Inputs!$B$7)-(U18-T18)/Inputs!$B$8 -> 275.3498 | AF18: =(SUMPRODUCT(V18:AE18/(1+Inputs!$B$24)^$B$7:$K$7)+U18*Inputs!$B$6*(1-Inputs!$B$7)*(1+Inputs!$B$17)*(1-Inputs!$B$17/Inputs!$B$18)/(Inputs!$B$24-Inputs!$B$17)/(1+Inputs!$B$24)^$K$7+Inputs!$B$9-Inputs!$B$10)/Inputs!$B$11 -> 22.667238
A19: 0.2 | B19: =$A19 -> 0.2 | C19: =$A19 -> 0.2 | D19: =$A19 -> 0.2 | E19: =$A19 -> 0.2 | F19: =$A19 -> 0.2 | G19: =$A19+(Inputs!$B$17-$A19)*(G$7-5)/5 -> 0.166 | H19: =$A19+(Inputs!$B$17-$A19)*(H$7-5)/5 -> 0.132 | I19: =$A19+(Inputs!$B$17-$A19)*(I$7-5)/5 -> 0.098 | J19: =$A19+(Inputs!$B$17-$A19)*(J$7-5)/5 -> 0.064 | K19: =$A19+(Inputs!$B$17-$A19)*(K$7-5)/5 -> 0.03 | L19: =Inputs!$B$5*(1+B19) -> 1200 | M19: =L19*(1+C19) -> 1440 | N19: =M19*(1+D19) -> 1728 | O19: =N19*(1+E19) -> 2073.6 | P19: =O19*(1+F19) -> 2488.32 | Q19: =P19*(1+G19) -> 2901.3811 | R19: =Q19*(1+H19) -> 3284.3634 | S19: =R19*(1+I19) -> 3606.231 | T19: =S19*(1+J19) -> 3837.0298 | U19: =T19*(1+K19) -> 3952.1407 | V19: =L19*Inputs!$B$6*(1-Inputs!$B$7)-(L19-Inputs!$B$5)/Inputs!$B$8 -> -55.818182 | W19: =M19*Inputs!$B$6*(1-Inputs!$B$7)-(M19-L19)/Inputs!$B$8 -> -66.981818 | X19: =N19*Inputs!$B$6*(1-Inputs!$B$7)-(N19-M19)/Inputs!$B$8 -> -80.378182 | Y19: =O19*Inputs!$B$6*(1-Inputs!$B$7)-(O19-N19)/Inputs!$B$8 -> -96.453818 | Z19: =P19*Inputs!$B$6*(1-Inputs!$B$7)-(P19-O19)/Inputs!$B$8 -> -115.74458 | AA19: =Q19*Inputs!$B$6*(1-Inputs!$B$7)-(Q19-P19)/Inputs!$B$8 -> -70.865091 | AB19: =R19*Inputs!$B$6*(1-Inputs!$B$7)-(R19-Q19)/Inputs!$B$8 -> -3.3075745 | AC19: =S19*Inputs!$B$6*(1-Inputs!$B$7)-(S19-R19)/Inputs!$B$8 -> 86.047336 | AD19: =T19*Inputs!$B$6*(1-Inputs!$B$7)-(T19-S19)/Inputs!$B$8 -> 193.07105 | AE19: =U19*Inputs!$B$6*(1-Inputs!$B$7)-(U19-T19)/Inputs!$B$8 -> 310.32851 | AF19: =(SUMPRODUCT(V19:AE19/(1+Inputs!$B$24)^$B$7:$K$7)+U19*Inputs!$B$6*(1-Inputs!$B$7)*(1+Inputs!$B$17)*(1-Inputs!$B$17/Inputs!$B$18)/(Inputs!$B$24-Inputs!$B$17)/(1+Inputs!$B$24)^$K$7+Inputs!$B$9-Inputs!$B$10)/Inputs!$B$11 -> 24.649378
A21: Reading the result: compare the implied growth with the base case (8%) and ask whether a firm with these margins and capital needs can deliver it.

Sheet Checks
A1: Integrity Checks
A3: Check | B3: Value | C3: Result
A4: Terminal growth is below WACC | B4: =Inputs!B17 -> 0.03 | C4: =IF(DCF!B12>Inputs!B17,"PASS","FAIL") -> PASS
A5: Terminal growth does not exceed the risk-free rate | B5: =Inputs!B17 -> 0.03 | C5: =IF(Inputs!B17<=Inputs!B12,"PASS","FAIL") -> PASS
A6: Terminal ROIC is at least WACC (no value-destroying growth) | B6: =Inputs!B18 -> 0.1 | C6: =IF(Inputs!B18>=DCF!B12,"PASS","FAIL") -> PASS
A7: Components sum to enterprise value | B7: =DCF!B24+DCF!B25+DCF!B26-DCF!B27 -> 0 | C7: =IF(ABS(B7)<0.000001,"PASS","FAIL") -> PASS
A8: Sensitivity base cell equals DCF value per share | B8: =Sensitivity!D8-DCF!B32 -> 0 | C8: =IF(ABS(B8)<0.000001,"PASS","FAIL") -> PASS
A9: Reverse-DCF 8% row equals DCF value per share (base growth path) | B9: =ReverseDCF!AF13-DCF!B32 -> 0 | C9: =IF(ABS(B9)<0.000001,"PASS","FAIL") -> PASS
A10: Year-10 growth equals terminal growth (smooth fade) | B10: =DCF!L4-Inputs!B17 -> 0 | C10: =IF(ABS(B10)<0.000001,"PASS","FAIL") -> PASS
A11: Value per share matches the chapter ($15.28) at the default inputs | B11: =DCF!B32 -> 15.280618 | C11: =IF(ABS(B11-15.28)<0.005,"PASS","INFO: inputs changed from chapter") -> PASS
A13: OVERALL | C13: =IF(COUNTIF(C4:C10,"FAIL")=0,"ALL CHECKS PASS","CHECK FAILED") -> ALL CHECKS PASS
A14: The chapter-value check (row 11) is informational and is excluded from the overall result because changing an input changes it by design.
