Workbook

Sheet README
A1: Example Co. Forecast and Valuation Model
A2: Companion workbook to the chapter Forecasting and Three-Statement Modeling. Example Co. is a teaching company; every figure is invented.
A4: Purpose | B4: Rebuilds the Example Co. model in the chapter: five-year income statement, balance sheet and cash flow statement, free cash flow, terminal value, equity value, sensitivity and consistency checks.
A5: How to use | B5: Change only blue cells on the Assumptions sheet. Every other sheet is formulas. With the starting inputs, equity value is 1,075.4 (chapter Section 4.3).
A6: Colour code | B6: Blue text = input you may change. Black = formula. Green = pure link from another sheet. Yellow fill = the two switches on Assumptions.
A7: Sheets | B7: Assumptions: all drivers and switches (chapter 2.6, 3.1, 4.3). Statements: income statement, balance sheet, cash flow statement (Section 3.3). Valuation: free cash flow, terminal value, equity bridge, terminal return table (Sections 4.1 to 4.3). Sensitivity: equity value against cost of capital and stable growth (Section 4.4). Checks: consistency tests (Section 5.1).
A8: Switches | B8: Assumptions B24: 1 = base growth and payout, 2 = stress case (20/15/12/10/8% growth, 50% payout). Assumptions B25: 1 = cash is the plug and debt stays constant; 2 = debt is the plug and cash is held at the minimum. To reproduce the stress table in Section 3.4, set B24 = 2, then compare B25 = 1 (negative cash) with B25 = 2 (debt rises to 687).
A9: Method notes | B9: Interest is charged on opening balances, so the model has no circular references. Cash on the balance sheet is the plug (total liabilities and equity less other assets); the cash flow statement is built independently and the Checks sheet confirms the two agree.
A10: Assumptions | B10: Cost of capital 9%, stable growth 3%, return on new capital in stable growth 10% and risk-free rate 4% are illustrative inputs chosen for teaching, not market data.
A11: Rounding | B11: Statements display whole numbers and the valuation shows one decimal; calculations use full precision.
A12: Sources | B12: See the footnotes and reference list in the chapter. Method follows the sales-driven pro forma approach and the stable-growth terminal value rules cited there.

Sheet Assumptions
A1: Assumptions
A2: Blue = input. All values for Example Co. are invented; year-0 figures come from the financial statements chapter.
A4: Operating drivers
A5: Year-0 revenue ($) | B5: 1000 | G5: Chapter 2 income statement
A6: Operating costs before depreciation (% of revenue) | B6: 0.8 | G6: 800 / 1,000; EBITDA margin = 1 - this
A7: Depreciation (% of revenue) | B7: 0.05 | G7: 50 / 1,000
A8: Receivables (% of revenue) | B8: 0.15 | G8: 150 / 1,000
A9: Inventory (% of revenue) | B9: 0.1 | G9: 100 / 1,000
A10: Payables and accruals (% of revenue) | B10: 0.1 | G10: 100 / 1,000
A11: Net fixed assets (% of revenue) | B11: 0.65 | G11: 650 / 1,000
A12: Intangibles ($, held constant) | B12: 100 | G12: No acquisitions or amortization
A13: Financing and tax
A14: Interest rate on opening debt | B14: 0.075 | G14: 30 / 400
A15: Interest rate on opening cash | B15: 0 | G15: None in the chapter
A16: Tax rate | B16: 0.3
A17: Dividend payout, base case (% of net income) | B17: 0.3 | G17: 25 / 84
A18: Dividend payout, stress case | B18: 0.5
A19: Minimum cash, debt-plug case ($) | B19: 50
A20: Year-0 cash ($) | B20: 100
A21: Year-0 debt ($) | B21: 400
A22: Year-0 shareholders' equity ($) | B22: 600
A23: Switches
A24: Growth and payout case (1 = base, 2 = stress) | B24: 1 | G24: Yellow = switch
A25: Plug (1 = cash, 2 = debt) | B25: 1 | G25: 1: debt constant, cash absorbs the gap. 2: borrow to hold minimum cash
A26: Active dividend payout | B26: =CHOOSE(B24,B17,B18) -> 0.3
A27: Revenue growth path
B28: Year 1 | C28: Year 2 | D28: Year 3 | E28: Year 4 | F28: Year 5
A29: Growth, base case | B29: 0.08 | C29: 0.07 | D29: 0.06 | E29: 0.05 | F29: 0.04
A30: Growth, stress case | B30: 0.2 | C30: 0.15 | D30: 0.12 | E30: 0.1 | F30: 0.08
A31: Active growth | B31: =CHOOSE($B$24,B29,B30) -> 0.08 | C31: =CHOOSE($B$24,C29,C30) -> 0.07 | D31: =CHOOSE($B$24,D29,D30) -> 0.06 | E31: =CHOOSE($B$24,E29,E30) -> 0.05 | F31: =CHOOSE($B$24,F29,F30) -> 0.04
A33: Valuation
A34: Cost of capital (WACC) | B34: 0.09 | G34: Illustrative
A35: Stable growth rate (g) | B35: 0.03 | G35: Cap at the risk-free rate
A36: Return on new capital in stable growth (ROC) | B36: 0.1 | G36: Growth creates value only above the cost of capital
A37: Risk-free rate (growth cap check) | B37: 0.04 | G37: Illustrative
A38: Mid-year discounting (0 = off, 1 = on) | B38: 0 | G38: 1 multiplies enterprise value by (1+WACC)^0.5
A40: Implied return on new capital from the forecast drivers | B40: =(1-B6-B7)*(1-B16)/(B8+B9-B10+B11) -> 0.13125 | G40: After-tax operating margin x marginal sales-to-capital (1 / capital per $ of revenue)

Sheet Statements
A1: Three-statement forecast ($)
A2: All cells are formulas except year-0 dividends (blue, from the financial statements chapter).
B3: Year 0 | C3: Year 1 | D3: Year 2 | E3: Year 3 | F3: Year 4 | G3: Year 5
A4: Income statement
A5: Revenues | B5: =Assumptions!B5 -> 1000 | C5: =B5*(1+Assumptions!B31) -> 1080 | D5: =C5*(1+Assumptions!C31) -> 1155.6 | E5: =D5*(1+Assumptions!D31) -> 1224.936 | F5: =E5*(1+Assumptions!E31) -> 1286.1828 | G5: =F5*(1+Assumptions!F31) -> 1337.6301
A6: Operating costs before depreciation | B6: =-Assumptions!$B$6*B5 -> -800 | C6: =-Assumptions!$B$6*C5 -> -864 | D6: =-Assumptions!$B$6*D5 -> -924.48 | E6: =-Assumptions!$B$6*E5 -> -979.9488 | F6: =-Assumptions!$B$6*F5 -> -1028.9462 | G6: =-Assumptions!$B$6*G5 -> -1070.1041
A7: EBITDA | B7: =B5+B6 -> 200 | C7: =C5+C6 -> 216 | D7: =D5+D6 -> 231.12 | E7: =E5+E6 -> 244.9872 | F7: =F5+F6 -> 257.23656 | G7: =G5+G6 -> 267.52602
A8: Depreciation | B8: =-Assumptions!$B$7*B5 -> -50 | C8: =-Assumptions!$B$7*C5 -> -54 | D8: =-Assumptions!$B$7*D5 -> -57.78 | E8: =-Assumptions!$B$7*E5 -> -61.2468 | F8: =-Assumptions!$B$7*F5 -> -64.30914 | G8: =-Assumptions!$B$7*G5 -> -66.881506
A9: Operating income (EBIT) | B9: =B7+B8 -> 150 | C9: =C7+C8 -> 162 | D9: =D7+D8 -> 173.34 | E9: =E7+E8 -> 183.7404 | F9: =F7+F8 -> 192.92742 | G9: =G7+G8 -> 200.64452
A10: Interest expense | B10: =-Assumptions!$B$14*B25 -> -30 | C10: =-Assumptions!$B$14*B25 -> -30 | D10: =-Assumptions!$B$14*C25 -> -30 | E10: =-Assumptions!$B$14*D25 -> -30 | F10: =-Assumptions!$B$14*E25 -> -30 | G10: =-Assumptions!$B$14*F25 -> -30
A11: Interest income on cash | B11: =0 -> 0 | C11: =Assumptions!$B$15*B18 -> 0 | D11: =Assumptions!$B$15*C18 -> 0 | E11: =Assumptions!$B$15*D18 -> 0 | F11: =Assumptions!$B$15*E18 -> 0 | G11: =Assumptions!$B$15*F18 -> 0
A12: Pre-tax income | B12: =B9+B10+B11 -> 120 | C12: =C9+C10+C11 -> 132 | D12: =D9+D10+D11 -> 143.34 | E12: =E9+E10+E11 -> 153.7404 | F12: =F9+F10+F11 -> 162.92742 | G12: =G9+G10+G11 -> 170.64452
A13: Taxes | B13: =-Assumptions!$B$16*MAX(B12,0) -> -36 | C13: =-Assumptions!$B$16*MAX(C12,0) -> -39.6 | D13: =-Assumptions!$B$16*MAX(D12,0) -> -43.002 | E13: =-Assumptions!$B$16*MAX(E12,0) -> -46.12212 | F13: =-Assumptions!$B$16*MAX(F12,0) -> -48.878226 | G13: =-Assumptions!$B$16*MAX(G12,0) -> -51.193355
A14: Net income | B14: =B12+B13 -> 84 | C14: =C12+C13 -> 92.4 | D14: =D12+D13 -> 100.338 | E14: =E12+E13 -> 107.61828 | F14: =F12+F13 -> 114.04919 | G14: =G12+G13 -> 119.45116
A15: Dividends | B15: -25 | C15: =-Assumptions!$B$26*C14 -> -27.72 | D15: =-Assumptions!$B$26*D14 -> -30.1014 | E15: =-Assumptions!$B$26*E14 -> -32.285484 | F15: =-Assumptions!$B$26*F14 -> -34.214758 | G15: =-Assumptions!$B$26*G14 -> -35.835349
A17: Balance sheet
A18: Cash (plug) | B18: =Assumptions!B20 -> 100 | C18: =C27-C19-C20-C21-C22 -> 100.68 | D18: =D27-D19-D20-D21-D22 -> 110.4366 | E18: =E27-E19-E20-E21-E22 -> 130.3006 | F18: =F27-F19-F20-F21-F22 -> 161.13759 | G18: =G27-G19-G20-G21-G22 -> 203.59556
A19: Receivables | B19: =Assumptions!$B$8*B5 -> 150 | C19: =Assumptions!$B$8*C5 -> 162 | D19: =Assumptions!$B$8*D5 -> 173.34 | E19: =Assumptions!$B$8*E5 -> 183.7404 | F19: =Assumptions!$B$8*F5 -> 192.92742 | G19: =Assumptions!$B$8*G5 -> 200.64452
A20: Inventory | B20: =Assumptions!$B$9*B5 -> 100 | C20: =Assumptions!$B$9*C5 -> 108 | D20: =Assumptions!$B$9*D5 -> 115.56 | E20: =Assumptions!$B$9*E5 -> 122.4936 | F20: =Assumptions!$B$9*F5 -> 128.61828 | G20: =Assumptions!$B$9*G5 -> 133.76301
A21: Net fixed assets | B21: =Assumptions!$B$11*B5 -> 650 | C21: =Assumptions!$B$11*C5 -> 702 | D21: =Assumptions!$B$11*D5 -> 751.14 | E21: =Assumptions!$B$11*E5 -> 796.2084 | F21: =Assumptions!$B$11*F5 -> 836.01882 | G21: =Assumptions!$B$11*G5 -> 869.45957
A22: Intangibles | B22: =Assumptions!$B$12 -> 100 | C22: =Assumptions!$B$12 -> 100 | D22: =Assumptions!$B$12 -> 100 | E22: =Assumptions!$B$12 -> 100 | F22: =Assumptions!$B$12 -> 100 | G22: =Assumptions!$B$12 -> 100
A23: Total assets | B23: =SUM(B18:B22) -> 1100 | C23: =SUM(C18:C22) -> 1172.68 | D23: =SUM(D18:D22) -> 1250.4766 | E23: =SUM(E18:E22) -> 1332.743 | F23: =SUM(F18:F22) -> 1418.7021 | G23: =SUM(G18:G22) -> 1507.4627
A24: Payables and accruals | B24: =Assumptions!$B$10*B5 -> 100 | C24: =Assumptions!$B$10*C5 -> 108 | D24: =Assumptions!$B$10*D5 -> 115.56 | E24: =Assumptions!$B$10*E5 -> 122.4936 | F24: =Assumptions!$B$10*F5 -> 128.61828 | G24: =Assumptions!$B$10*G5 -> 133.76301
A25: Debt | B25: =Assumptions!B21 -> 400 | C25: =IF(Assumptions!$B$25=1,B25,MAX(B25,B25+Assumptions!$B$19-(B18+C33+C34+C36))) -> 400 | D25: =IF(Assumptions!$B$25=1,C25,MAX(C25,C25+Assumptions!$B$19-(C18+D33+D34+D36))) -> 400 | E25: =IF(Assumptions!$B$25=1,D25,MAX(D25,D25+Assumptions!$B$19-(D18+E33+E34+E36))) -> 400 | F25: =IF(Assumptions!$B$25=1,E25,MAX(E25,E25+Assumptions!$B$19-(E18+F33+F34+F36))) -> 400 | G25: =IF(Assumptions!$B$25=1,F25,MAX(F25,F25+Assumptions!$B$19-(F18+G33+G34+G36))) -> 400
A26: Shareholders' equity | B26: =Assumptions!B22 -> 600 | C26: =B26+C14+C15 -> 664.68 | D26: =C26+D14+D15 -> 734.9166 | E26: =D26+E14+E15 -> 810.2494 | F26: =E26+F14+F15 -> 890.08383 | G26: =F26+G14+G15 -> 973.69965
A27: Total liabilities and equity | B27: =B24+B25+B26 -> 1100 | C27: =C24+C25+C26 -> 1172.68 | D27: =D24+D25+D26 -> 1250.4766 | E27: =E24+E25+E26 -> 1332.743 | F27: =F24+F25+F26 -> 1418.7021 | G27: =G24+G25+G26 -> 1507.4627
A29: Cash flow statement
A30: Net income | C30: =C14 -> 92.4 | D30: =D14 -> 100.338 | E30: =E14 -> 107.61828 | F30: =F14 -> 114.04919 | G30: =G14 -> 119.45116
A31: + Depreciation | C31: =-C8 -> 54 | D31: =-D8 -> 57.78 | E31: =-E8 -> 61.2468 | F31: =-F8 -> 64.30914 | G31: =-G8 -> 66.881506
A32: - Increase in working capital | C32: =-((C19+C20-C24)-(B19+B20-B24)) -> -12 | D32: =-((D19+D20-D24)-(C19+C20-C24)) -> -11.34 | E32: =-((E19+E20-E24)-(D19+D20-D24)) -> -10.4004 | F32: =-((F19+F20-F24)-(E19+E20-E24)) -> -9.18702 | G32: =-((G19+G20-G24)-(F19+F20-F24)) -> -7.7170968
A33: Cash flow from operations | C33: =SUM(C30:C32) -> 134.4 | D33: =SUM(D30:D32) -> 146.778 | E33: =SUM(E30:E32) -> 158.46468 | F33: =SUM(F30:F32) -> 169.17131 | G33: =SUM(G30:G32) -> 178.61557
A34: Capital expenditures | C34: =-((C21-B21)-C8) -> -106 | D34: =-((D21-C21)-D8) -> -106.92 | E34: =-((E21-D21)-E8) -> -106.3152 | F34: =-((F21-E21)-F8) -> -104.11956 | G34: =-((G21-F21)-G8) -> -100.32226
A35: Cash flow from investing | C35: =C34 -> -106 | D35: =D34 -> -106.92 | E35: =E34 -> -106.3152 | F35: =F34 -> -104.11956 | G35: =G34 -> -100.32226
A36: Dividends | C36: =C15 -> -27.72 | D36: =D15 -> -30.1014 | E36: =E15 -> -32.285484 | F36: =F15 -> -34.214758 | G36: =G15 -> -35.835349
A37: Net borrowing | C37: =C25-B25 -> 0 | D37: =D25-C25 -> 0 | E37: =E25-D25 -> 0 | F37: =F25-E25 -> 0 | G37: =G25-F25 -> 0
A38: Cash flow from financing | C38: =C36+C37 -> -27.72 | D38: =D36+D37 -> -30.1014 | E38: =E36+E37 -> -32.285484 | F38: =F36+F37 -> -34.214758 | G38: =G36+G37 -> -35.835349
A39: Net change in cash | C39: =C33+C35+C38 -> 0.68 | D39: =D33+D35+D38 -> 9.7566 | E39: =E33+E35+E38 -> 19.863996 | F39: =F33+F35+F38 -> 30.836996 | G39: =G33+G35+G38 -> 42.457964
A40: Change in balance-sheet cash | C40: =C18-B18 -> 0.68 | D40: =D18-C18 -> 9.7566 | E40: =E18-D18 -> 19.863996 | F40: =F18-E18 -> 30.836996 | G40: =G18-F18 -> 42.457964

Sheet Valuation
A1: Free cash flow and valuation ($)
A2: Uses the Statements sheet and the valuation inputs on Assumptions (cost of capital, stable growth, return on new capital).
C3: Year 1 | D3: Year 2 | E3: Year 3 | F3: Year 4 | G3: Year 5
A4: Year number | C4: 1 | D4: 2 | E4: 3 | F4: 4 | G4: 5
A5: EBIT x (1 - tax rate) | C5: =Statements!C9*(1-Assumptions!$B$16) -> 113.4 | D5: =Statements!D9*(1-Assumptions!$B$16) -> 121.338 | E5: =Statements!E9*(1-Assumptions!$B$16) -> 128.61828 | F5: =Statements!F9*(1-Assumptions!$B$16) -> 135.04919 | G5: =Statements!G9*(1-Assumptions!$B$16) -> 140.45116
A6: + Depreciation | C6: =-Statements!C8 -> 54 | D6: =-Statements!D8 -> 57.78 | E6: =-Statements!E8 -> 61.2468 | F6: =-Statements!F8 -> 64.30914 | G6: =-Statements!G8 -> 66.881506
A7: - Capital expenditures | C7: =Statements!C34 -> -106 | D7: =Statements!D34 -> -106.92 | E7: =Statements!E34 -> -106.3152 | F7: =Statements!F34 -> -104.11956 | G7: =Statements!G34 -> -100.32226
A8: - Increase in working capital | C8: =Statements!C32 -> -12 | D8: =Statements!D32 -> -11.34 | E8: =Statements!E32 -> -10.4004 | F8: =Statements!F32 -> -9.18702 | G8: =Statements!G32 -> -7.7170968
A9: Free cash flow to the firm (FCFF) | C9: =SUM(C5:C8) -> 49.4 | D9: =SUM(D5:D8) -> 60.858 | E9: =SUM(E5:E8) -> 73.14948 | F9: =SUM(F5:F8) -> 86.051754 | G9: =SUM(G5:G8) -> 99.293312
A10: Net reinvestment (NOPAT - FCFF) | C10: =C5-C9 -> 64 | D10: =D5-D9 -> 60.48 | E10: =E5-E9 -> 55.4688 | F10: =F5-F9 -> 48.99744 | G10: =G5-G9 -> 41.15785
A11: Discount factor | C11: =1/(1+Assumptions!$B$34)^(C4-0.5*Assumptions!$B$38) -> 0.91743119 | D11: =1/(1+Assumptions!$B$34)^(D4-0.5*Assumptions!$B$38) -> 0.84167999 | E11: =1/(1+Assumptions!$B$34)^(E4-0.5*Assumptions!$B$38) -> 0.77218348 | F11: =1/(1+Assumptions!$B$34)^(F4-0.5*Assumptions!$B$38) -> 0.70842521 | G11: =1/(1+Assumptions!$B$34)^(G4-0.5*Assumptions!$B$38) -> 0.64993139
A12: Present value of FCFF | C12: =C9*C11 -> 45.321101 | D12: =D9*D11 -> 51.222961 | E12: =E9*E11 -> 56.48482 | F12: =F9*F11 -> 60.961232 | G12: =G9*G11 -> 64.53384
A14: Terminal value and equity value
A15: Year-5 after-tax operating income | B15: =G5 -> 140.45116
A16: Year-6 after-tax operating income | B16: =B15*(1+Assumptions!B35) -> 144.6647
A17: Stable reinvestment rate (g / ROC) | B17: =Assumptions!B35/Assumptions!B36 -> 0.3
A18: Year-6 free cash flow | B18: =B16*(1-B17) -> 101.26529
A19: Terminal value at end of year 5 | B19: =IF(Assumptions!B34>Assumptions!B35,B18/(Assumptions!B34-Assumptions!B35),0) -> 1687.7548 | C19: Returns 0 if WACC is not above g (see Checks)
A20: Present value of terminal value | B20: =B19*G11 -> 1096.9248
A21: Present value of year 1-5 FCFF | B21: =SUM(C12:G12) -> 278.52395
A22: Enterprise value | B22: =B20+B21 -> 1375.4488
A23: + Cash (year 0) | B23: =Statements!B18 -> 100
A24: - Debt (year 0) | B24: =-Statements!B25 -> -400
A25: Equity value | B25: =B22+B23+B24 -> 1075.4488
A26: Terminal value as share of enterprise value | B26: =IF(B22=0,0,B20/B22) -> 0.79750321
A27: Enterprise value / year-0 EBITDA | B27: =B22/Statements!B7 -> 6.8772438
A29: What the terminal return on capital is worth
A30: Terminal-period assumption | B30: ROC | C30: Reinvestment | D30: Terminal value | E30: Enterprise value | F30: Equity value
A31: Return on capital = cost of capital | B31: =Assumptions!B34 -> 0.09 | C31: =Assumptions!$B$35/B31 -> 0.33333333 | D31: =IF(Assumptions!$B$34>Assumptions!$B$35,$B$16*(1-C31)/(Assumptions!$B$34-Assumptions!$B$35),0) -> 1607.3855 | E31: =$B$21+D31*$G$11 -> 1323.2143 | F31: =E31+$B$23+$B$24 -> 1023.2143
A32: Return on capital = input on Assumptions | B32: =Assumptions!B36 -> 0.1 | C32: =Assumptions!$B$35/B32 -> 0.3 | D32: =IF(Assumptions!$B$34>Assumptions!$B$35,$B$16*(1-C32)/(Assumptions!$B$34-Assumptions!$B$35),0) -> 1687.7548 | E32: =$B$21+D32*$G$11 -> 1375.4488 | F32: =E32+$B$23+$B$24 -> 1075.4488
A33: Return on new capital implied by the forecast | B33: =Assumptions!B40 -> 0.13125 | C33: =Assumptions!$B$35/B33 -> 0.22857143 | D33: =IF(Assumptions!$B$34>Assumptions!$B$35,$B$16*(1-C33)/(Assumptions!$B$34-Assumptions!$B$35),0) -> 1859.9747 | E33: =$B$21+D33*$G$11 -> 1487.3799 | F33: =E33+$B$23+$B$24 -> 1187.3799
A34: No reinvestment (growth for free) | B34: n/a | C34: 0 | D34: =IF(Assumptions!$B$34>Assumptions!$B$35,$B$16*(1-C34)/(Assumptions!$B$34-Assumptions!$B$35),0) -> 2411.0783 | E34: =$B$21+D34*$G$11 -> 1845.5594 | F34: =E34+$B$23+$B$24 -> 1545.5594

Sheet Sensitivity
A1: Equity value ($): cost of capital against stable growth
A2: Uses the return on new capital on Assumptions. Blue headers can be changed. 'n/m' = cost of capital not above growth.
A4: Cost of capital (down) / growth (across) | B4: 0.02 | C4: 0.025 | D4: 0.03 | E4: 0.035 | F4: 0.04
A5: 0.08 | B5: =IF($A5<=B$4,"n/m",SUMPRODUCT(Valuation!$C$9:$G$9/(1+$A5)^(Valuation!$C$4:$G$4-0.5*Assumptions!$B$38))+Valuation!$G$5*(1+B$4)*(1-B$4/Assumptions!$B$36)/($A5-B$4)/(1+$A5)^(5-0.5*Assumptions!$B$38)+Valuation!$B$23+Valuation!$B$24) -> 1286.8194 | C5: =IF($A5<=C$4,"n/m",SUMPRODUCT(Valuation!$C$9:$G$9/(1+$A5)^(Valuation!$C$4:$G$4-0.5*Assumptions!$B$38))+Valuation!$G$5*(1+C$4)*(1-C$4/Assumptions!$B$36)/($A5-C$4)/(1+$A5)^(5-0.5*Assumptions!$B$38)+Valuation!$B$23+Valuation!$B$24) -> 1322.8824 | D5: =IF($A5<=D$4,"n/m",SUMPRODUCT(Valuation!$C$9:$G$9/(1+$A5)^(Valuation!$C$4:$G$4-0.5*Assumptions!$B$38))+Valuation!$G$5*(1+D$4)*(1-D$4/Assumptions!$B$36)/($A5-D$4)/(1+$A5)^(5-0.5*Assumptions!$B$38)+Valuation!$B$23+Valuation!$B$24) -> 1365.2021 | E5: =IF($A5<=E$4,"n/m",SUMPRODUCT(Valuation!$C$9:$G$9/(1+$A5)^(Valuation!$C$4:$G$4-0.5*Assumptions!$B$38))+Valuation!$G$5*(1+E$4)*(1-E$4/Assumptions!$B$36)/($A5-E$4)/(1+$A5)^(5-0.5*Assumptions!$B$38)+Valuation!$B$23+Valuation!$B$24) -> 1415.8641 | F5: =IF($A5<=F$4,"n/m",SUMPRODUCT(Valuation!$C$9:$G$9/(1+$A5)^(Valuation!$C$4:$G$4-0.5*Assumptions!$B$38))+Valuation!$G$5*(1+F$4)*(1-F$4/Assumptions!$B$36)/($A5-F$4)/(1+$A5)^(5-0.5*Assumptions!$B$38)+Valuation!$B$23+Valuation!$B$24) -> 1477.9968
A6: 0.09 | B6: =IF($A6<=B$4,"n/m",SUMPRODUCT(Valuation!$C$9:$G$9/(1+$A6)^(Valuation!$C$4:$G$4-0.5*Assumptions!$B$38))+Valuation!$G$5*(1+B$4)*(1-B$4/Assumptions!$B$36)/($A6-B$4)/(1+$A6)^(5-0.5*Assumptions!$B$38)+Valuation!$B$23+Valuation!$B$24) -> 1042.6301 | C6: =IF($A6<=C$4,"n/m",SUMPRODUCT(Valuation!$C$9:$G$9/(1+$A6)^(Valuation!$C$4:$G$4-0.5*Assumptions!$B$38))+Valuation!$G$5*(1+C$4)*(1-C$4/Assumptions!$B$36)/($A6-C$4)/(1+$A6)^(5-0.5*Assumptions!$B$38)+Valuation!$B$23+Valuation!$B$24) -> 1058.1283 | D6: =IF($A6<=D$4,"n/m",SUMPRODUCT(Valuation!$C$9:$G$9/(1+$A6)^(Valuation!$C$4:$G$4-0.5*Assumptions!$B$38))+Valuation!$G$5*(1+D$4)*(1-D$4/Assumptions!$B$36)/($A6-D$4)/(1+$A6)^(5-0.5*Assumptions!$B$38)+Valuation!$B$23+Valuation!$B$24) -> 1075.4488 | E6: =IF($A6<=E$4,"n/m",SUMPRODUCT(Valuation!$C$9:$G$9/(1+$A6)^(Valuation!$C$4:$G$4-0.5*Assumptions!$B$38))+Valuation!$G$5*(1+E$4)*(1-E$4/Assumptions!$B$36)/($A6-E$4)/(1+$A6)^(5-0.5*Assumptions!$B$38)+Valuation!$B$23+Valuation!$B$24) -> 1095.0886 | F6: =IF($A6<=F$4,"n/m",SUMPRODUCT(Valuation!$C$9:$G$9/(1+$A6)^(Valuation!$C$4:$G$4-0.5*Assumptions!$B$38))+Valuation!$G$5*(1+F$4)*(1-F$4/Assumptions!$B$36)/($A6-F$4)/(1+$A6)^(5-0.5*Assumptions!$B$38)+Valuation!$B$23+Valuation!$B$24) -> 1117.7435
A7: 0.1 | B7: =IF($A7<=B$4,"n/m",SUMPRODUCT(Valuation!$C$9:$G$9/(1+$A7)^(Valuation!$C$4:$G$4-0.5*Assumptions!$B$38))+Valuation!$G$5*(1+B$4)*(1-B$4/Assumptions!$B$36)/($A7-B$4)/(1+$A7)^(5-0.5*Assumptions!$B$38)+Valuation!$B$23+Valuation!$B$24) -> 860.12412 | C7: =IF($A7<=C$4,"n/m",SUMPRODUCT(Valuation!$C$9:$G$9/(1+$A7)^(Valuation!$C$4:$G$4-0.5*Assumptions!$B$38))+Valuation!$G$5*(1+C$4)*(1-C$4/Assumptions!$B$36)/($A7-C$4)/(1+$A7)^(5-0.5*Assumptions!$B$38)+Valuation!$B$23+Valuation!$B$24) -> 864.48458 | D7: =IF($A7<=D$4,"n/m",SUMPRODUCT(Valuation!$C$9:$G$9/(1+$A7)^(Valuation!$C$4:$G$4-0.5*Assumptions!$B$38))+Valuation!$G$5*(1+D$4)*(1-D$4/Assumptions!$B$36)/($A7-D$4)/(1+$A7)^(5-0.5*Assumptions!$B$38)+Valuation!$B$23+Valuation!$B$24) -> 868.84503 | E7: =IF($A7<=E$4,"n/m",SUMPRODUCT(Valuation!$C$9:$G$9/(1+$A7)^(Valuation!$C$4:$G$4-0.5*Assumptions!$B$38))+Valuation!$G$5*(1+E$4)*(1-E$4/Assumptions!$B$36)/($A7-E$4)/(1+$A7)^(5-0.5*Assumptions!$B$38)+Valuation!$B$23+Valuation!$B$24) -> 873.20549 | F7: =IF($A7<=F$4,"n/m",SUMPRODUCT(Valuation!$C$9:$G$9/(1+$A7)^(Valuation!$C$4:$G$4-0.5*Assumptions!$B$38))+Valuation!$G$5*(1+F$4)*(1-F$4/Assumptions!$B$36)/($A7-F$4)/(1+$A7)^(5-0.5*Assumptions!$B$38)+Valuation!$B$23+Valuation!$B$24) -> 877.56595
A8: 0.11 | B8: =IF($A8<=B$4,"n/m",SUMPRODUCT(Valuation!$C$9:$G$9/(1+$A8)^(Valuation!$C$4:$G$4-0.5*Assumptions!$B$38))+Valuation!$G$5*(1+B$4)*(1-B$4/Assumptions!$B$36)/($A8-B$4)/(1+$A8)^(5-0.5*Assumptions!$B$38)+Valuation!$B$23+Valuation!$B$24) -> 718.71028 | C8: =IF($A8<=C$4,"n/m",SUMPRODUCT(Valuation!$C$9:$G$9/(1+$A8)^(Valuation!$C$4:$G$4-0.5*Assumptions!$B$38))+Valuation!$G$5*(1+C$4)*(1-C$4/Assumptions!$B$36)/($A8-C$4)/(1+$A8)^(5-0.5*Assumptions!$B$38)+Valuation!$B$23+Valuation!$B$24) -> 716.8308 | D8: =IF($A8<=D$4,"n/m",SUMPRODUCT(Valuation!$C$9:$G$9/(1+$A8)^(Valuation!$C$4:$G$4-0.5*Assumptions!$B$38))+Valuation!$G$5*(1+D$4)*(1-D$4/Assumptions!$B$36)/($A8-D$4)/(1+$A8)^(5-0.5*Assumptions!$B$38)+Valuation!$B$23+Valuation!$B$24) -> 714.19544 | E8: =IF($A8<=E$4,"n/m",SUMPRODUCT(Valuation!$C$9:$G$9/(1+$A8)^(Valuation!$C$4:$G$4-0.5*Assumptions!$B$38))+Valuation!$G$5*(1+E$4)*(1-E$4/Assumptions!$B$36)/($A8-E$4)/(1+$A8)^(5-0.5*Assumptions!$B$38)+Valuation!$B$23+Valuation!$B$24) -> 710.65302 | F8: =IF($A8<=F$4,"n/m",SUMPRODUCT(Valuation!$C$9:$G$9/(1+$A8)^(Valuation!$C$4:$G$4-0.5*Assumptions!$B$38))+Valuation!$G$5*(1+F$4)*(1-F$4/Assumptions!$B$36)/($A8-F$4)/(1+$A8)^(5-0.5*Assumptions!$B$38)+Valuation!$B$23+Valuation!$B$24) -> 706.00919
A10: Check: base cell equals Valuation equity value only if WACC = 9% and g = 3% are on the grid.

Sheet Checks
A1: Consistency checks
A2: PASS/FAIL tests from Section 5.1 of the chapter. Tolerance 0.01 unless stated.
A4: Check | B4: Year 1 | C4: Year 2 | D4: Year 3 | E4: Year 4 | F4: Year 5 | H4: Result | I4: What it tests
A5: Assets - liabilities and equity | B5: =Statements!C23-Statements!C27 -> 0 | C5: =Statements!D23-Statements!D27 -> 0 | D5: =Statements!E23-Statements!E27 -> 0 | E5: =Statements!F23-Statements!F27 -> 0 | F5: =Statements!G23-Statements!G27 -> 0 | H5: =IF(MAX(ABS(B5),ABS(C5),ABS(D5),ABS(E5),ABS(F5))<0.01,"PASS","FAIL") -> PASS | I5: Balance sheet balances every year
A6: Cash flow statement - balance sheet cash change | B6: =Statements!C39-Statements!C40 -> 1.6697754e-13 | C6: =Statements!D39-Statements!D40 -> -1.8474111e-13 | D6: =Statements!E39-Statements!E40 -> 2.2026825e-13 | E6: =Statements!F39-Statements!F40 -> -3.126388e-13 | F6: =Statements!G39-Statements!G40 -> 0 | H6: =IF(MAX(ABS(B6),ABS(C6),ABS(D6),ABS(E6),ABS(F6))<0.01,"PASS","FAIL") -> PASS | I6: Independent cash reconciliation
A7: Cash balance | B7: =Statements!C18 -> 100.68 | C7: =Statements!D18 -> 110.4366 | D7: =Statements!E18 -> 130.3006 | E7: =Statements!F18 -> 161.13759 | F7: =Statements!G18 -> 203.59556 | H7: =IF(MIN(B7:F7)>=0,"PASS","FAIL") -> PASS | I7: Cash never negative (fails in stress case with cash plug)
A8: NOPAT growth | B8: =Valuation!C5/(Statements!B9*(1-Assumptions!$B$16))-1 -> 0.08 | C8: =Valuation!D5/Valuation!C5-1 -> 0.07 | D8: =Valuation!E5/Valuation!D5-1 -> 0.06 | E8: =Valuation!F5/Valuation!E5-1 -> 0.05 | F8: =Valuation!G5/Valuation!F5-1 -> 0.04 | I8: Growth in after-tax operating income
A9: Net reinvestment / prior NOPAT x return on new capital | B9: =Valuation!C10/(Statements!B9*(1-Assumptions!$B$16))*Assumptions!$B$40 -> 0.08 | C9: =Valuation!D10/Valuation!C5*Assumptions!$B$40 -> 0.07 | D9: =Valuation!E10/Valuation!D5*Assumptions!$B$40 -> 0.06 | E9: =Valuation!F10/Valuation!E5*Assumptions!$B$40 -> 0.05 | F9: =Valuation!G10/Valuation!F5*Assumptions!$B$40 -> 0.04 | H9: =IF(MAX(ABS(B9-B8),ABS(C9-C8),ABS(D9-D8),ABS(E9-E8),ABS(F9-F8))<0.0005,"PASS","FAIL") -> PASS | I9: Growth is paid for by reinvestment (rows 8 and 9 agree)
A11: Terminal value tests
A12: Stable growth at or below the risk-free rate | H12: =IF(Assumptions!B35<=Assumptions!B37,"PASS","FAIL") -> PASS | I12: Cap growth at the risk-free rate
A13: Cost of capital above stable growth | H13: =IF(Assumptions!B34>Assumptions!B35,"PASS","FAIL") -> PASS | I13: Terminal value formula is valid
A14: Return on new capital at or above the cost of capital | H14: =IF(Assumptions!B36>=Assumptions!B34,"PASS","FAIL") -> PASS | I14: If FAIL, growth destroys value
A15: Terminal value share of enterprise value below 90% | H15: =IF(Valuation!B26<0.9,"PASS","FAIL") -> PASS | I15: Flag only; a high share is normal but needs credible assumptions
A17: Overall | H17: =IF(COUNTIF(H5:H15,"FAIL")=0,"ALL PASS",COUNTIF(H5:H15,"FAIL")&" FAIL") -> ALL PASS
